polydatum/__init__.py
polydatum/config.py
polydatum/context.py
polydatum/dal.py
polydatum/errors.py
polydatum/resources.py
polydatum/services.py
polydatum/util.py
polydatum-0.9.1.dist-info/LICENSE
polydatum-0.9.1.dist-info/METADATA
polydatum-0.9.1.dist-info/WHEEL
polydatum-0.9.1.dist-info/top_level.txt
polydatum-0.9.1.dist-info/RECORD
