Metadata-Version: 2.1
Name: polydatum
Version: 0.9.1
Summary: An encapsulated persistance layer for Python
Home-page: https://github.com/plynth/polydatum
Author: Mike Thornton
Author-email: six8@devdetails.com
License: MIT
Keywords: orm,persistence
Platform: UNKNOWN
Classifier: Programming Language :: Python
Classifier: Intended Audience :: Developers
Classifier: License :: OSI Approved :: MIT License
Classifier: Natural Language :: English
Classifier: Topic :: Software Development :: Libraries :: Python Modules
Classifier: Programming Language :: Python
Classifier: Programming Language :: Python :: 2.7
Classifier: Programming Language :: Python :: 3
Classifier: Programming Language :: Python :: 3.6
Classifier: Programming Language :: Python :: 3.7
Requires-Dist: six (>=1.12.0)
Requires-Dist: werkzeug
